Workbook

Sheet INDICE
A1: [CLIENTE] | D1: CONTROLLO CONTABILE TRIMESTRALE | M1: [PERIODO]
A3: NORMATIVA DI RIFERIMENTO: PRINCIPIO DI REVISIONE (SA ITALIA) 250B
A5: DATA INVIO RICHIESTA | H5: CONCLUSIONE DEI CONTROLLI
A6: DATA SVOLGIMENTO ATTIVITA'
A8: INDICE DELLE CARTE DI LAVORO
A9: Sez. | B9: Argomento | F9: Status
A10: A | B10: Sistema di controllo interno
A11: B | B11: Libri obbligatori
A12: C | B12: Adempimenti tributari e previdenziali
A13: D | B13: Test su rilevazioni contabili
A14: E | B14: Disponibilità liquide
A15: F | B15: Lettura verbali degli Organi sociali e di Controllo
A16: G | B16: Analisi situazione contabile periodica
A17: H | B17: Colloqui con la Direzione
A18: I | B18: Operazioni particolarmente significative
A20: RIFERIMENTI INTERNI
A21: Nome - Funzione | C21: E-mail | E21: Telefono
A27: TEAM REVISIONE
A28: Attività svolta da
A29: Rivista da

Sheet Richiesta doc
A1: =+INDICE!A1
A2: richieste per controllo contabile ex art. 2409 – ter c.c.
D3: [T-2] | I3: [T-1] | N3: [Trimestre corrente]
A4: A. INFORMAZIONI DI CARATTERE GENERALE | D4: Date rif. | E4: Note cliente | F4: Note BT | G4: Doc. ricevuto | I4: Date rif. | J4: Note cliente | K4: Note BT | L4: Doc. ricevuto | N4: Date rif. | O4: Note cliente | P4: Note BT | Q4: Doc. ricevuto
A5: A.1 | B5: Informazioni in merito a eventuali significativi cambiamenti nel sistema di controllo interno intervenuti nel periodo, in particolare per quanto riguarda il sistema contabile-amministrativo.
A6: A.2 | B6: Informazioni in merito a: • eventuali cambiamenti significativi nella struttura organizzativa e/o commerciale; • operazioni di entità particolarmente significativa o caratterizzate da elevata rischiosità; • contratti stipulati dalla società di eccezionale rilevanza o per operazioni di carattere straordinario e impegni significativi assunti nel periodo; • acquisizioni, cessioni, o liquidazioni di significative attività, già verificatesi o previste, e relativo trattamento contabile; • passività potenziali: nuovi procedimenti legali e sviluppi di quelli precedenti; • significativi cambiamenti nella situazione finanziaria della società, nuovi prestiti, garanzie ricevute o concesse, eventuali difficoltà nell'ottenimento del credito o nel far fronte agli impegni assunti.
A7: A.3 | B7: Copia di eventuali cartelle ricevute, comunicazioni, avvisi bonari ricevuti dalle autorità fiscali, previdenziali o qualsiasi altro organi di controllo nel periodo oggetto di verifica
A8: A.4 | B8: Informazioni e documentazione su transazioni finanziare non ordinarie (per importi non marginali), a titolo di esempio: bonifici da/per paesi a fiscalità privilegiata, trasferimenti fra società del gruppo non ordinari (diversi dalla nomale gestione cash pooling e dai finanziamenti da/verso controllante), compravendite inusuali e/o movimenti finanziari che esulano dal business tipico della società.
A10: B. BILANCIO E SCRITTURE CONTABILI
A11: B.1 | B11: Bilancino di verifica (in txt o excel)
A12: B.2 | B12: Conto economico gestionale confrontato con il budget
A13: B.3 | B13: Budget anno 2026 con previsione cashflow a 6-12 mesi se disponibile
A14: B.4 | B14: Estrazione libro giornale provvisorio (o mastrini), in formato txt
A16: C. LIBRI SOCIALI
A17: C.1 | B17: Copia verbali Assemblee soci
A18: C.2 | B18: Copia verbali Consiglio di amministrazione
A19: C.3 | B19: Copia verbali Collegio sindacale
A20: C.4 | B20: Eventuali annotazioni sul libro soci
A21: Nel caso in cui vi siano verbali non ancora riportati a libro, ci occorre la bozza del verbale.
A23: D. LIBRI FISCALI / CONTABILI
A24: D.1 | B24: Libro giornale in stampa definitiva (scansione prima e ultima pagina del bollato), se disponibile
A25: D.2 | B25: Libro inventari in stampa definitiva
A26: D.3 | B26: Registri Iva
A28: E. ADEMPIMENTI TRIBUTARI
A29: E.1 | B29: Quietanze F24 versati/da versare/compensati nel periodo
A30: E.2 | B30: Ricevute versamenti Alifond, FASA, Previndai, Anima, FASI, Enasarco
A31: E.3 | B31: Comunicazione liquidazione periodica IVA
A32: E.4 | B32: Dichiarazione annuale IVA
A33: E.5 | B33: Ricevute invio dichiarazioni Intrastat
A35: F. BANCHE
A36: F.1 | B36: Estratti conto bancari
A37: F.2 | B37: Riconciliazioni bancarie
A38: F.3 | B38: Report Centrale Rischi o documento equivalente
A40: G. PERSONALE
A41: G.1 | B41: Cedolone, prospetto contabile e prima nota contabile
A42: G.2 | B42: Contabile pagamento stipendi

Sheet A
A1: Cliente | B1: =+INDICE!A1 | G1: ← INDICE
A2: Periodo rif. | B2: =+INDICE!M1
A3: Fatto da | B3: =INDICE!C28
A4: Rivisto da | B4: =+INDICE!C29
A5: Data | B5: =INDICE!F6
A7: SEZIONE A - SISTEMA DI CONTROLLO INTERNO

Sheet B
A1: Cliente | B1: =+INDICE!A1 | G1: ← INDICE
A2: Periodo rif. | B2: =+INDICE!M1
A3: Fatto da | B3: =INDICE!C28
A4: Rivisto da | B4: =+INDICE!C29
A5: Data | B5: =INDICE!F6
A7: SEZIONE B - LIBRI OBBLIGATORI
A9: RILEVAZIONE ULTIMO AGGIORNAMENTO
A10: Libro | C10: Nr.reg. | D10: Data reg. | E10: Pag. | F10: Descrizione registrazione | G10: Note
A11: Libro giornale definitivo
A12: Libro giornale provvisorio anno in corso
A13: Registro Beni Ammortizzabili
A14: Registro IVA acquisti
A15: Libro unico del lavoro

Sheet C
A1: Cliente | B1: =+INDICE!A1 | M1: ← INDICE
A2: Periodo rif. | B2: =+INDICE!M1
A3: Fatto da | B3: =INDICE!C28
A4: Rivisto da | B4: =+INDICE!C29
A5: Data | B5: =INDICE!F6
A7: SEZIONE C - ADEMPIMENTI TRIBUTARI E PREVIDENZIALI
A9: VERSAMENTI / COMPENSAZIONI F24
A10: Data rif.
A11: Data vers.
A12: Importo
A13: Nr. prot.
A17: VERSAMENTI / ADEMPIMENTI TRIMESTRALI
A18: Vers./ademp. | B18: 1° trim. 2026 | C18: 2° trim. 2026 | D18: 3° trim. 2026 | E18: 4° trim. 2026
A19: [FONDO]
A20: [FONDO]
A21: [FONDO]
A22: [FONDO]
A23: [FONDO]
A24: LIPE
A26: ALTRI VERSAMENTI / ADEMPIMENTI ANNUALI
A27: Vers./ademp. | C27: Data invio | D27: Nr. Protocollo
A28: TASSA ANNUALE LIBRI SOCI (ct 7085)

Sheet D
A1: Cliente | B1: =+INDICE!A1 | M1: ← INDICE
A2: Periodo rif. | B2: =+INDICE!M1
A3: Fatto da | B3: =INDICE!C28
A4: Rivisto da | B4: =+INDICE!C29
A5: Data | B5: =INDICE!F6
A7: SEZIONE D - TEST SU RILEVAZIONI CONTABILI

Sheet E
A1: Cliente | B1: =+INDICE!A1 | I1: ← INDICE
A2: Periodo rif. | B2: =+INDICE!M1
A3: Fatto da | B3: =INDICE!C28
A4: Rivisto da | B4: =+INDICE!C29
A5: Data | B5: =INDICE!F6
A7: SEZIONE E - DISPONIBILITA' LIQUIDE
A9: RICONCILIAZIONI BANCARIE
E10: Riconciliazioni bancarie
A11: Co.ge | B11: Banca | C11: Tipo conto | D11: N° conto | E11: Saldo co.ge | F11: Saldo e/c | G11: Sospesi | H11: Check | I11: Note BT
H12: =E12-F12
H13: =E13-F13
H14: =E14-F14
H15: =E15-F15
H16: =E16-F16
H17: =E17-F17
H18: =E18-F18
H19: =E19-F19
H20: =E20-F20
H21: =E21-F21
H22: =E22-F22
H23: =E23-F23
... H28: =E28-F28
D29: Totale | E29: =SUM(E12:E28) | F29: =SUM(F12:F28) | G29: =SUM(G12:G28) | H29: =SUM(H12:H28)

Sheet F
A1: Cliente | B1: =+INDICE!A1 | E1: ← INDICE
A2: Periodo rif. | B2: =+INDICE!M1
A3: Fatto da | B3: =INDICE!C28
A4: Rivisto da | B4: =+INDICE!C29
A5: Data | B5: =INDICE!F6
A7: SEZIONE F - LETTURA VERBALI DEGLI ORGANI SOCIALI E DI CONTROLLO
A9: LIBRO | C9: Ultima pagina compilata | D9: Data ultimo verbale a libro | E9: Ultimo verbale in bozza | F9: Note
B10: Libro dei soci
B11: Libro verbali ASSEMBLEE
B12: Libro Obbligazione
B13: Libro verbali del Consiglio di Amministrazione

Sheet G
A1: Cliente | B1: =+INDICE!A1 | E1: ← INDICE
A2: Periodo rif. | B2: =+INDICE!M1
A3: Fatto da | B3: =INDICE!C28
A4: Rivisto da | B4: =+INDICE!C29
A5: Data | B5: =INDICE!F6
A7: SEZIONE G - ANALISI SITUAZIONE CONTABILE PERIODICA
B9: acc nb | D9: Account | E9: Saldo periodo | F9: Saldo N-1 | G9: Amount Chg | H9: %Chg

Sheet H
A1: Cliente | B1: =+INDICE!A1 | E1: ← INDICE
A2: Periodo rif. | B2: =+INDICE!M1
A3: Fatto da | B3: =INDICE!C28
A4: Rivisto da | B4: =+INDICE!C29
A5: Data | B5: =INDICE!F6
A7: SEZIONE H - COLLOQUI CON LA DIREZIONE

Sheet I
A1: Cliente | B1: =+INDICE!A1 | E1: ← INDICE
A2: Periodo rif. | B2: =+INDICE!M1
A3: Fatto da | B3: =INDICE!C28
A4: Rivisto da | B4: =+INDICE!C29
A5: Data | B5: =INDICE!F6
A7: SEZIONE I - OPERAZIONI PARTICOLARMENTE SIGNIFICATIVE

Sheet DS_INTERNAL_DOCUMENT_STORAGE

Sheet DS_INTERNAL_SETTINGS_STORAGE

Sheet DS_INTERNAL_DOCGROUP_STORAGE

Sheet DS_INTERNAL_SNIP_STORAGE
